odoo10_addon_product_code_remove-10.0.0.0.0.99.dev1-nspkg.pth
odoo/addons/product_code_remove/README.rst
odoo/addons/product_code_remove/__init__.py
odoo/addons/product_code_remove/__manifest__.py
odoo/addons/product_code_remove/i18n/product_code_remove.pot
odoo/addons/product_code_remove/models/__init__.py
odoo/addons/product_code_remove/models/product_product.py
odoo/addons/product_code_remove/static/description/icon.png
odoo/addons/product_code_remove/tests/__init__.py
odoo/addons/product_code_remove/tests/test_product_code.py
odoo10_addon_product_code_remove-10.0.0.0.0.99.dev1.dist-info/METADATA
odoo10_addon_product_code_remove-10.0.0.0.0.99.dev1.dist-info/WHEEL
odoo10_addon_product_code_remove-10.0.0.0.0.99.dev1.dist-info/namespace_packages.txt
odoo10_addon_product_code_remove-10.0.0.0.0.99.dev1.dist-info/top_level.txt
odoo10_addon_product_code_remove-10.0.0.0.0.99.dev1.dist-info/RECORD
