Metadata-Version: 2.1
Name: odoo10-addon-product-code-remove
Version: 10.0.0.0.0.99.dev1
Summary: Remove Product Code from sale order line name
Home-page: https://github.com/oca/product-attribute
Author: Therp BV,Odoo Community Association (OCA)
Author-email: support@odoo-community.org
License: AGPL-3
Platform: UNKNOWN
Classifier: Programming Language :: Python
Classifier: Framework :: Odoo
Classifier: License :: OSI Approved :: GNU Affero General Public License v3
Requires-Python: ~=2.7
Requires-Dist: odoo (<10.1dev,>=10.0)
